xcrypto/__init__.py
xcrypto/xcrypto.py
xcrypto-1.3.1.dist-info/LICENSE
xcrypto-1.3.1.dist-info/METADATA
xcrypto-1.3.1.dist-info/WHEEL
xcrypto-1.3.1.dist-info/entry_points.txt
xcrypto-1.3.1.dist-info/top_level.txt
xcrypto-1.3.1.dist-info/RECORD
